grades/__init__.py
grades/gradient_early_stopping.py
grades/vlm_early_stopping.py
grades-1.0.6.dist-info/licenses/LICENSE
grades-1.0.6.dist-info/METADATA
grades-1.0.6.dist-info/WHEEL
grades-1.0.6.dist-info/top_level.txt
grades-1.0.6.dist-info/RECORD
