Metadata-Version: 2.4
Name: grades
Version: 1.0.6
Summary: Gradient-based Early Stopping for Efficient Fine-tuning
Home-page: https://github.com/IXZZZ9/GradES
Maintainer-email: Xi Zeng <zengxi0115@gmail.com>
License: MIT
Project-URL: Homepage, https://github.com/IXZZZ9/GradES
Project-URL: Documentation, https://github.com/IXZZZ9/GradES#readme
Project-URL: Repository, https://github.com/IXZZZ9/GradES.git
Project-URL: Bug Tracker, https://github.com/IXZZZ9/GradES/issues
Project-URL: Paper, https://arxiv.org/abs/2509.01842
Keywords: machine learning,deep learning,transformers,early stopping,gradient-based,fine-tuning,llm,pytorch,huggingface,efficiency
Classifier: Development Status :: 4 - Beta
Classifier: Intended Audience :: Developers
Classifier: Intended Audience :: Science/Research
Classifier: License :: OSI Approved :: MIT License
Classifier: Operating System :: OS Independent
Classifier: Programming Language :: Python :: 3
Classifier: Programming Language :: Python :: 3.8
Classifier: Programming Language :: Python :: 3.9
Classifier: Programming Language :: Python :: 3.10
Classifier: Programming Language :: Python :: 3.11
Classifier: Programming Language :: Python :: 3.12
Classifier: Topic :: Scientific/Engineering :: Artificial Intelligence
Classifier: Topic :: Software Development :: Libraries :: Python Modules
Requires-Python: >=3.8
License-File: LICENSE
Requires-Dist: torch>=1.9.0
Requires-Dist: transformers>=4.20.0
Requires-Dist: numpy>=1.21.0
Provides-Extra: wandb
Requires-Dist: wandb>=0.12.0; extra == "wandb"
Provides-Extra: dev
Requires-Dist: pytest>=6.0; extra == "dev"
Requires-Dist: pytest-cov>=2.0; extra == "dev"
Requires-Dist: black>=22.0; extra == "dev"
Requires-Dist: isort>=5.0; extra == "dev"
Requires-Dist: flake8>=4.0; extra == "dev"
Requires-Dist: mypy>=0.910; extra == "dev"
Provides-Extra: examples
Requires-Dist: jupyter>=1.0.0; extra == "examples"
Requires-Dist: notebook>=6.0.0; extra == "examples"
Requires-Dist: ipywidgets>=7.0.0; extra == "examples"
Requires-Dist: trl>=0.7.0; extra == "examples"
Requires-Dist: unsloth; extra == "examples"
Dynamic: home-page
Dynamic: license-file
Dynamic: requires-python
